appium/__init__.py
appium/py.typed
appium/version.py
appium/common/__init__.py
appium/common/exceptions.py
appium/common/helper.py
appium/common/logger.py
appium/options/__init__.py
appium/options/android/__init__.py
appium/options/android/common/__init__.py
appium/options/android/common/adb/__init__.py
appium/options/android/common/adb/adb_exec_timeout_option.py
appium/options/android/common/adb/adb_port_option.py
appium/options/android/common/adb/allow_delay_adb_option.py
appium/options/android/common/adb/build_tools_version_option.py
appium/options/android/common/adb/clear_device_logs_on_start_option.py
appium/options/android/common/adb/ignore_hidden_api_policy_error_option.py
appium/options/android/common/adb/logcat_filter_specs_option.py
appium/options/android/common/adb/logcat_format_option.py
appium/options/android/common/adb/mock_location_app_option.py
appium/options/android/common/adb/remote_adb_host_option.py
appium/options/android/common/adb/skip_logcat_capture_option.py
appium/options/android/common/adb/suppress_kill_server_option.py
appium/options/android/common/app/__init__.py
appium/options/android/common/app/allow_test_packages_option.py
appium/options/android/common/app/android_install_timeout_option.py
appium/options/android/common/app/app_activity_option.py
appium/options/android/common/app/app_package_option.py
appium/options/android/common/app/app_wait_activity_option.py
appium/options/android/common/app/app_wait_duration_option.py
appium/options/android/common/app/app_wait_for_launch_option.py
appium/options/android/common/app/app_wait_package_option.py
appium/options/android/common/app/auto_grant_premissions_option.py
appium/options/android/common/app/enforce_app_install_option.py
appium/options/android/common/app/intent_action_option.py
appium/options/android/common/app/intent_category_option.py
appium/options/android/common/app/intent_flags_option.py
appium/options/android/common/app/optional_intent_arguments_option.py
appium_python_client-5.2.5.dist-info/METADATA
appium_python_client-5.2.5.dist-info/WHEEL
appium_python_client-5.2.5.dist-info/licenses/LICENSE
appium_python_client-5.2.5.dist-info/RECORD
